README.md
setup.cfg
setup.py
spacy_hunspell/__init__.py
spacy_hunspell/_about.py
spacy_hunspell.egg-info/PKG-INFO
spacy_hunspell.egg-info/SOURCES.txt
spacy_hunspell.egg-info/dependency_links.txt
spacy_hunspell.egg-info/not-zip-safe
spacy_hunspell.egg-info/requires.txt
spacy_hunspell.egg-info/top_level.txt