Metadata-Version: 1.0
Name: spacy-hunspell
Version: 0.1.0
Summary: spaCy extension for Hunspell.
Home-page: https://github.com/tokestermw/spacy_hunspell
Author: Motoki Wu
Author-email: tokestermw@gmail.com
License: MIT
Platform: UNKNOWN
